Metadata-Version: 2.1
Name: martinsimplecalculator
Version: 0.0.3
Summary: a basic calculator
Home-page: UNKNOWN
Author: Martin Husby
Author-email: martin.husby.dev@gmail.com
License: MIT
Keywords: calculator
Platform: UNKNOWN
Classifier: Development Status :: 5 - Production/Stable
Classifier: Intended Audience :: Education
Classifier: Operating System :: Microsoft :: Windows :: Windows 10
Classifier: License :: OSI Approved :: MIT License
Classifier: Programming Language :: Python :: 3
